probability_graphic/__init__.py
probability_graphic/probability_graphic.py
probability_graphic-1.0.0.dist-info/METADATA
probability_graphic-1.0.0.dist-info/WHEEL
probability_graphic-1.0.0.dist-info/top_level.txt
probability_graphic-1.0.0.dist-info/RECORD
