Metadata-Version: 2.1
Name: probability-graphic
Version: 1.0.0
Summary: Gráficas de probabilidad por consola
Home-page: UNKNOWN
Author: Granpepinillo
Author-email: granpepinillo@gmail.com
License: UNKNOWN
Keywords: python,probabilidad,graficas,porcentajes
Platform: UNKNOWN
Classifier: Development Status :: 3 - Alpha
Classifier: Intended Audience :: Education
Classifier: Programming Language :: Python :: 2
Classifier: Programming Language :: Python :: 3
Classifier: Operating System :: MacOS :: MacOS X
Classifier: Operating System :: Microsoft :: Windows
